{
  "info": {
    "_postman_id": "09e4e4ad-8442-4a7d-99df-b18719e6ffa2",
    "name": "Flight Booking REST API",
    "schema": "https://schema.getpostman.com/json/collection/v2.1.0/collection.json",
    "_exporter_id": "27341475"
  },
  "item": [
    {
      "name": "Auth",
      "item": [
        {
          "name": "auth-register",
          "request": {
            "method": "POST",
            "header": [
              {
                "key": "Content-Type",
                "value": "application/json",
                "type": "text"
              }
            ],
            "body": {
              "mode": "raw",
              "raw": "{\r\n  \"name\": \"Rohit Sharma\",\r\n  \"email\": \"rohitjadaun014@gmail.com\",\r\n  \"password\": \"rohit@123\",\r\n  \"role\": \"user\",\r\n  \"profilePicture\": \"https://i.pravatar.cc/150\",\r\n  \"gender\": \"male\"\r\n}",
              "options": {
                "raw": {
                  "language": "json"
                }
              }
            },
            "url": {
              "raw": "http://localhost:3000/api/auth/register",
              "protocol": "http",
              "host": ["localhost"],
              "port": "3000",
              "path": ["api", "auth", "register"]
            }
          },
          "response": []
        },
        {
          "name": "auth-register-admin",
          "request": {
            "method": "POST",
            "header": [
              {
                "key": "Content-Type",
                "value": "application/json",
                "type": "text"
              }
            ],
            "body": {
              "mode": "raw",
              "raw": "{\r\n  \"name\": \"Admin User\",\r\n  \"email\": \"admin@gmail.com\",\r\n  \"password\": \"admin@123\",\r\n  \"role\": \"admin\",\r\n  \"profilePicture\": \"https://i.pravatar.cc/150\",\r\n  \"gender\": \"male\"\r\n}",
              "options": {
                "raw": {
                  "language": "json"
                }
              }
            },
            "url": {
              "raw": "http://localhost:3000/api/auth/register",
              "protocol": "http",
              "host": ["localhost"],
              "port": "3000",
              "path": ["api", "auth", "register"]
            }
          },
          "response": []
        },
        {
          "name": "auth-login",
          "request": {
            "method": "POST",
            "header": [
              {
                "key": "Content-Type",
                "value": "application/json",
                "type": "text"
              }
            ],
            "body": {
              "mode": "raw",
              "raw": "{\r\n  \"email\": \"rohitjadaun014@gmail.com\",\r\n  \"password\": \"rohit@123\"\r\n}",
              "options": {
                "raw": {
                  "language": "json"
                }
              }
            },
            "url": {
              "raw": "http://localhost:3000/api/auth/login",
              "protocol": "http",
              "host": ["localhost"],
              "port": "3000",
              "path": ["api", "auth", "login"]
            }
          },
          "response": []
        },
        {
          "name": "auth-login-admin",
          "request": {
            "method": "POST",
            "header": [
              {
                "key": "Content-Type",
                "value": "application/json",
                "type": "text"
              }
            ],
            "body": {
              "mode": "raw",
              "raw": "{\r\n  \"email\": \"admin@gmail.com\",\r\n  \"password\": \"admin@123\"\r\n}",
              "options": {
                "raw": {
                  "language": "json"
                }
              }
            },
            "url": {
              "raw": "http://localhost:3000/api/auth/login",
              "protocol": "http",
              "host": ["localhost"],
              "port": "3000",
              "path": ["api", "auth", "login"]
            }
          },
          "response": []
        },
        {
          "name": "auth-logout",
          "request": {
            "method": "POST",
            "header": [
              {
                "key": "Authorization",
                "value": "Bearer <your_token>",
                "type": "text"
              }
            ],
            "body": {
              "mode": "raw",
              "raw": "",
              "options": {
                "raw": {
                  "language": "json"
                }
              }
            },
            "url": {
              "raw": "http://localhost:3000/api/auth/logout",
              "protocol": "http",
              "host": ["localhost"],
              "port": "3000",
              "path": ["api", "auth", "logout"]
            }
          },
          "response": []
        }
      ]
    },
    {
      "name": "Users",
      "item": [
        {
          "name": "User-GetUser-Details",
          "request": {
            "method": "GET",
            "header": [
              {
                "key": "Authorization",
                "value": "Bearer <your_token>",
                "type": "text"
              }
            ],
            "url": {
              "raw": "http://localhost:3000/api/users/",
              "protocol": "http",
              "host": ["localhost"],
              "port": "3000",
              "path": ["api", "users", ""]
            }
          },
          "response": []
        },
        {
          "name": "User-UpdateUser-profile",
          "request": {
            "method": "POST",
            "header": [
              {
                "key": "Authorization",
                "value": "Bearer <your_token>",
                "type": "text"
              }
            ],
            "body": {
              "mode": "formdata",
              "formdata": [
                {
                  "key": "name",
                  "value": "Rohit Sharma Updated",
                  "type": "text"
                },
                {
                  "key": "gender",
                  "value": "male",
                  "type": "text"
                },
                {
                  "key": "avatar",
                  "type": "file",
                  "src": ""
                }
              ]
            },
            "url": {
              "raw": "http://localhost:3000/api/users/profile",
              "protocol": "http",
              "host": ["localhost"],
              "port": "3000",
              "path": ["api", "users", "profile"]
            }
          },
          "response": []
        }
      ]
    },
    {
      "name": "Flights",
      "item": [
        {
          "name": "admin-Create-flight",
          "request": {
            "method": "POST",
            "header": [
              {
                "key": "Authorization",
                "value": "Bearer <admin_token>",
                "type": "text"
              }
            ],
            "body": {
              "mode": "formdata",
              "formdata": [
                { "key": "flightNumber", "value": "AI-101", "type": "text" },
                { "key": "airline", "value": "Air India", "type": "text" },
                { "key": "departureCity", "value": "Delhi", "type": "text" },
                { "key": "arrivalCity", "value": "Mumbai", "type": "text" },
                { "key": "departureDate", "value": "2026-08-01", "type": "text" },
                { "key": "arrivalDate", "value": "2026-08-01", "type": "text" },
                { "key": "price", "value": "5000", "type": "text" },
                { "key": "availableSeats", "value": "100", "type": "text" },
                { "key": "flightClass", "value": "Economy", "type": "text" },
                { "key": "image", "type": "file", "src": "" }
              ]
            },
            "url": {
              "raw": "http://localhost:3000/api/flights",
              "protocol": "http",
              "host": ["localhost"],
              "port": "3000",
              "path": ["api", "flights"]
            }
          },
          "response": []
        },
        {
          "name": "admin-Update-flight-byID",
          "request": {
            "method": "PUT",
            "header": [
              {
                "key": "Authorization",
                "value": "Bearer <admin_token>",
                "type": "text"
              },
              {
                "key": "Content-Type",
                "value": "application/json",
                "type": "text"
              }
            ],
            "body": {
              "mode": "raw",
              "raw": "{\r\n  \"price\": 4500,\r\n  \"availableSeats\": 120\r\n}",
              "options": {
                "raw": {
                  "language": "json"
                }
              }
            },
            "url": {
              "raw": "http://localhost:3000/api/flights/<flight_id>",
              "protocol": "http",
              "host": ["localhost"],
              "port": "3000",
              "path": ["api", "flights", "<flight_id>"]
            }
          },
          "response": []
        },
        {
          "name": "admin-Delete-flight-byID",
          "request": {
            "method": "DELETE",
            "header": [
              {
                "key": "Authorization",
                "value": "Bearer <admin_token>",
                "type": "text"
              }
            ],
            "url": {
              "raw": "http://localhost:3000/api/flights/<flight_id>",
              "protocol": "http",
              "host": ["localhost"],
              "port": "3000",
              "path": ["api", "flights", "<flight_id>"]
            }
          },
          "response": []
        },
        {
          "name": "User-GetAll-flights",
          "request": {
            "method": "GET",
            "header": [],
            "url": {
              "raw": "http://localhost:3000/api/flights",
              "protocol": "http",
              "host": ["localhost"],
              "port": "3000",
              "path": ["api", "flights"]
            }
          },
          "response": []
        },
        {
          "name": "User-GetFlight-byID",
          "request": {
            "method": "GET",
            "header": [],
            "url": {
              "raw": "http://localhost:3000/api/flights/<flight_id>",
              "protocol": "http",
              "host": ["localhost"],
              "port": "3000",
              "path": ["api", "flights", "<flight_id>"]
            }
          },
          "response": []
        },
        {
          "name": "Pagination-Page1",
          "request": {
            "method": "GET",
            "header": [],
            "url": {
              "raw": "http://localhost:3000/api/flights?page=1&limit=6",
              "protocol": "http",
              "host": ["localhost"],
              "port": "3000",
              "path": ["api", "flights"],
              "query": [
                { "key": "page", "value": "1" },
                { "key": "limit", "value": "6" }
              ]
            }
          },
          "response": []
        },
        {
          "name": "Pagination-Page2",
          "request": {
            "method": "GET",
            "header": [],
            "url": {
              "raw": "http://localhost:3000/api/flights?page=2&limit=6",
              "protocol": "http",
              "host": ["localhost"],
              "port": "3000",
              "path": ["api", "flights"],
              "query": [
                { "key": "page", "value": "2" },
                { "key": "limit", "value": "6" }
              ]
            }
          },
          "response": []
        },
        {
          "name": "Sort-Price-LowToHigh",
          "request": {
            "method": "GET",
            "header": [],
            "url": {
              "raw": "http://localhost:3000/api/flights?sortBy=price&order=asc",
              "protocol": "http",
              "host": ["localhost"],
              "port": "3000",
              "path": ["api", "flights"],
              "query": [
                { "key": "sortBy", "value": "price" },
                { "key": "order", "value": "asc" }
              ]
            }
          },
          "response": []
        },
        {
          "name": "Sort-Price-HighToLow",
          "request": {
            "method": "GET",
            "header": [],
            "url": {
              "raw": "http://localhost:3000/api/flights?sortBy=price&order=desc",
              "protocol": "http",
              "host": ["localhost"],
              "port": "3000",
              "path": ["api", "flights"],
              "query": [
                { "key": "sortBy", "value": "price" },
                { "key": "order", "value": "desc" }
              ]
            }
          },
          "response": []
        },
        {
          "name": "Sort-Seats-MostAvailable",
          "request": {
            "method": "GET",
            "header": [],
            "url": {
              "raw": "http://localhost:3000/api/flights?sortBy=availableSeats&order=desc",
              "protocol": "http",
              "host": ["localhost"],
              "port": "3000",
              "path": ["api", "flights"],
              "query": [
                { "key": "sortBy", "value": "availableSeats" },
                { "key": "order", "value": "desc" }
              ]
            }
          },
          "response": []
        },
        {
          "name": "Sort-Date-Earliest",
          "request": {
            "method": "GET",
            "header": [],
            "url": {
              "raw": "http://localhost:3000/api/flights?sortBy=departureDate&order=asc",
              "protocol": "http",
              "host": ["localhost"],
              "port": "3000",
              "path": ["api", "flights"],
              "query": [
                { "key": "sortBy", "value": "departureDate" },
                { "key": "order", "value": "asc" }
              ]
            }
          },
          "response": []
        },
        {
          "name": "Filter-DepartureCity-lowercase",
          "request": {
            "method": "GET",
            "header": [],
            "url": {
              "raw": "http://localhost:3000/api/flights?departureCity=delhi",
              "protocol": "http",
              "host": ["localhost"],
              "port": "3000",
              "path": ["api", "flights"],
              "query": [
                { "key": "departureCity", "value": "delhi" }
              ]
            }
          },
          "response": []
        },
        {
          "name": "Filter-DepartureCity-uppercase",
          "request": {
            "method": "GET",
            "header": [],
            "url": {
              "raw": "http://localhost:3000/api/flights?departureCity=DELHI",
              "protocol": "http",
              "host": ["localhost"],
              "port": "3000",
              "path": ["api", "flights"],
              "query": [
                { "key": "departureCity", "value": "DELHI" }
              ]
            }
          },
          "response": []
        },
        {
          "name": "Filter-ArrivalCity",
          "request": {
            "method": "GET",
            "header": [],
            "url": {
              "raw": "http://localhost:3000/api/flights?arrivalCity=Mumbai",
              "protocol": "http",
              "host": ["localhost"],
              "port": "3000",
              "path": ["api", "flights"],
              "query": [
                { "key": "arrivalCity", "value": "Mumbai" }
              ]
            }
          },
          "response": []
        },
        {
          "name": "Filter-FlightClass-Business",
          "request": {
            "method": "GET",
            "header": [],
            "url": {
              "raw": "http://localhost:3000/api/flights?flightClass=Business",
              "protocol": "http",
              "host": ["localhost"],
              "port": "3000",
              "path": ["api", "flights"],
              "query": [
                { "key": "flightClass", "value": "Business" }
              ]
            }
          },
          "response": []
        },
        {
          "name": "Filter-FlightClass-Economy",
          "request": {
            "method": "GET",
            "header": [],
            "url": {
              "raw": "http://localhost:3000/api/flights?flightClass=Economy",
              "protocol": "http",
              "host": ["localhost"],
              "port": "3000",
              "path": ["api", "flights"],
              "query": [
                { "key": "flightClass", "value": "Economy" }
              ]
            }
          },
          "response": []
        },
        {
          "name": "Filter-FlightClass-First",
          "request": {
            "method": "GET",
            "header": [],
            "url": {
              "raw": "http://localhost:3000/api/flights?flightClass=First",
              "protocol": "http",
              "host": ["localhost"],
              "port": "3000",
              "path": ["api", "flights"],
              "query": [
                { "key": "flightClass", "value": "First" }
              ]
            }
          },
          "response": []
        },
        {
          "name": "Filter-DepartureDate",
          "request": {
            "method": "GET",
            "header": [],
            "url": {
              "raw": "http://localhost:3000/api/flights?departureDate=2026-08-01",
              "protocol": "http",
              "host": ["localhost"],
              "port": "3000",
              "path": ["api", "flights"],
              "query": [
                { "key": "departureDate", "value": "2026-08-01" }
              ]
            }
          },
          "response": []
        },
        {
          "name": "Combined-Filter-Sort-Pagination",
          "request": {
            "method": "GET",
            "header": [],
            "url": {
              "raw": "http://localhost:3000/api/flights?departureCity=delhi&sortBy=price&order=asc&page=1&limit=3",
              "protocol": "http",
              "host": ["localhost"],
              "port": "3000",
              "path": ["api", "flights"],
              "query": [
                { "key": "departureCity", "value": "delhi" },
                { "key": "sortBy", "value": "price" },
                { "key": "order", "value": "asc" },
                { "key": "page", "value": "1" },
                { "key": "limit", "value": "3" }
              ]
            }
          },
          "response": []
        }
      ]
    },
    {
      "name": "Bookings",
      "item": [
        {
          "name": "bookings-Create-Booking",
          "request": {
            "method": "POST",
            "header": [
              {
                "key": "Authorization",
                "value": "Bearer <user_token>",
                "type": "text"
              },
              {
                "key": "Content-Type",
                "value": "application/json",
                "type": "text"
              }
            ],
            "body": {
              "mode": "raw",
              "raw": "{\r\n  \"flightId\": \"<flight_id>\",\r\n  \"passengerList\": [\r\n    {\r\n      \"name\": \"Rohit Sharma\",\r\n      \"age\": 21,\r\n      \"gender\": \"male\"\r\n    },\r\n    {\r\n      \"name\": \"Priya Sharma\",\r\n      \"age\": 24,\r\n      \"gender\": \"female\"\r\n    }\r\n  ]\r\n}",
              "options": {
                "raw": {
                  "language": "json"
                }
              }
            },
            "url": {
              "raw": "http://localhost:3000/api/bookings",
              "protocol": "http",
              "host": ["localhost"],
              "port": "3000",
              "path": ["api", "bookings"]
            }
          },
          "response": []
        },
        {
          "name": "booking-Get-By-ID",
          "request": {
            "method": "GET",
            "header": [
              {
                "key": "Authorization",
                "value": "Bearer <your_token>",
                "type": "text"
              }
            ],
            "url": {
              "raw": "http://localhost:3000/api/bookings/<booking_id>",
              "protocol": "http",
              "host": ["localhost"],
              "port": "3000",
              "path": ["api", "bookings", "<booking_id>"]
            }
          },
          "response": []
        },
        {
          "name": "booking-Update",
          "request": {
            "method": "PUT",
            "header": [
              {
                "key": "Authorization",
                "value": "Bearer <user_token>",
                "type": "text"
              },
              {
                "key": "Content-Type",
                "value": "application/json",
                "type": "text"
              }
            ],
            "body": {
              "mode": "raw",
              "raw": "{\r\n  \"passengerList\": [\r\n    {\r\n      \"name\": \"Rohit Sharma Updated\",\r\n      \"age\": 22,\r\n      \"gender\": \"male\"\r\n    }\r\n  ]\r\n}",
              "options": {
                "raw": {
                  "language": "json"
                }
              }
            },
            "url": {
              "raw": "http://localhost:3000/api/bookings/<booking_id>",
              "protocol": "http",
              "host": ["localhost"],
              "port": "3000",
              "path": ["api", "bookings", "<booking_id>"]
            }
          },
          "response": []
        },
        {
          "name": "booking-Cancel-refund-ADMIN",
          "request": {
            "method": "PUT",
            "header": [
              {
                "key": "Authorization",
                "value": "Bearer <admin_token>",
                "type": "text"
              }
            ],
            "url": {
              "raw": "http://localhost:3000/api/bookings/<booking_id>/cancel",
              "protocol": "http",
              "host": ["localhost"],
              "port": "3000",
              "path": ["api", "bookings", "<booking_id>", "cancel"]
            }
          },
          "response": []
        },
        {
          "name": "booking-Cancel-USER-blocked-403",
          "request": {
            "method": "PUT",
            "header": [
              {
                "key": "Authorization",
                "value": "Bearer <user_token>",
                "type": "text"
              }
            ],
            "url": {
              "raw": "http://localhost:3000/api/bookings/<booking_id>/cancel",
              "protocol": "http",
              "host": ["localhost"],
              "port": "3000",
              "path": ["api", "bookings", "<booking_id>", "cancel"]
            }
          },
          "response": []
        }
      ]
    }
  ]
}
